{
   "type": "entity",
   "components": {
      "unit_info": {
         "display_name": "i18n(brewerymod:entities.plants.blueberry.display_name)",
         "description": "i18n(brewerymod:entities.plants.blueberry.description)",
         "icon" : "file(blueberry.png)"
      },
      "render_info" : {
         "scale" : 0.2
      },
      "model_variants": {
         "default": {
            "models": [
               "file(blueberry.qb)"
            ]
         }
      },
      "mob" : {
         "model_origin" : { "x": 0, "y": 0, "z": 0 }
      }
   }
}
 