{
	"mixins": "stonehearth:mixins:item_properties",
		"type": "entity",
		"components": {
			"item": {
         	"category" : "Tasty Beverage",
				"stacks" : 8,
				"max_stacks" : 8
			},
			"model_variants": {
				"default": {
				"models": [
				"file(strawberry_wine.qb)"
				]
			}
		},
		"unit_info": {
			"name": "Strawberry Wine",
			"description": "Packed with sweet goodness!",
			"icon" : "file(strawberry_wine.png)"
		},
		"stonehearth:material" : {
			"tags" :  "resource food_container strawberry_wine"
		},
		"mob" : {
			"model_origin" : { "x": 0, "y": 0, "z": 0.05 }
			},
      "render_info" : {
         "scale" : 0.045
      	}
		},
		"entity_data" : {
			"stonehearth:food_container" : {
			"effect": "fiddle",
			"food": "brewerymod:cooking:strawberry_wine_serving",
			"stacks_per_serving": 1
		},
		"stonehearth:net_worth" : {
			"value_in_gold" : 3,
			"rarity" : "common",
			"shop_info" : {
			"buyable" : true,   
			"sellable" : true,
			"shopkeeper_level" : 1,
			"shopkeeper_type" : "caravan"
			}
		}
	}
}